src/toolkit-gm/__init__.py
src/toolkit-gm/data_analyse.py
src/toolkit-gm/database.py
src/toolkit-gm/eta.py
src/toolkit-gm/magic_run.py
src/toolkit-gm/misc.py
toolkit_gm-0.0.2.dist-info/METADATA
toolkit_gm-0.0.2.dist-info/WHEEL
toolkit_gm-0.0.2.dist-info/licenses/LICENSE
toolkit_gm-0.0.2.dist-info/RECORD
